ballista/__init__.py
ballista-0.0.1a0.dist-info/LICENSE
ballista-0.0.1a0.dist-info/METADATA
ballista-0.0.1a0.dist-info/WHEEL
ballista-0.0.1a0.dist-info/top_level.txt
ballista-0.0.1a0.dist-info/RECORD
