Metadata-Version: 2.1
Name: ballista
Version: 0.0.1a0
Summary: Helpers for training with pytorch
Home-page: https://github.com/cceyda/Ballista
Author: Ceyda Cinarel
Author-email: snu_ceyda@gmail.com
License: UNKNOWN
Download-URL: https://github.com/cceyda/Ballista/archive/v0.0.1-alpha.tar.gz
Platform: UNKNOWN
Classifier: Programming Language :: Python :: 3
Classifier: License :: OSI Approved :: MIT License
Classifier: Operating System :: OS Independent
Requires-Python: >=3.6
Requires-Dist: pyyaml
Requires-Dist: coloredlogs
